rfslib/__init__.py
rfslib/abstract_pconnection.py
rfslib/fs_pconnection.py
rfslib/ftp_pconnection.py
rfslib/path_utils.py
rfslib/pconnection_settings.py
rfslib/pglobber.py
rfslib/pinstance.py
rfslib/sftp_pconnection.py
rfslib/smb12_pconnection.py
rfslib/smb23_pconnection.py
rfslib-3.1.9.dist-info/LICENSE
rfslib-3.1.9.dist-info/METADATA
rfslib-3.1.9.dist-info/WHEEL
rfslib-3.1.9.dist-info/top_level.txt
rfslib-3.1.9.dist-info/RECORD
