Metadata-Version: 2.1
Name: rfslib
Version: 3.1.9
Summary: Remote file system libraries for data manipulation between remote /and local host/ (cp, mv, ls, rm,..)
Home-page: https://git.profinit.eu/pstastny/rfslib
Author: Přemysl Šťastný
Author-email: p-w@stty.cz
License-File: LICENSE
Requires-Dist: pysmb <2,>=1.2.7
Requires-Dist: paramiko <3,>=2.7.2
Requires-Dist: smbprotocol <2,>=1.6.1
Requires-Dist: ftputil <6,>=5.0.1
